majormode/__init__.py
majormode/perseus/__init__.py
majormode/perseus/client/__init__.py
majormode/perseus/client/service/__init__.py
majormode/perseus/client/service/sim_card/__init__.py
majormode/perseus/client/service/sim_card/sim_card_service.py
majormode/perseus/client/service/tracker/__init__.py
majormode/perseus/client/service/tracker/tracker_service.py
majormode/perseus/client/service/wap/__init__.py
majormode/perseus/client/service/wap/wap_service.py
xeberus_restful_api_client_library-1.0.0.dist-info/METADATA
xeberus_restful_api_client_library-1.0.0.dist-info/WHEEL
xeberus_restful_api_client_library-1.0.0.dist-info/top_level.txt
xeberus_restful_api_client_library-1.0.0.dist-info/RECORD
